osbot_llms/OSBot_LLMs__Server_Config.py
osbot_llms/OSBot_LLMs__Shared_Objects.py
osbot_llms/__init__.py
osbot_llms/backend/__init__.py
osbot_llms/backend/s3_minio/S3_DB__Chat_Threads.py
osbot_llms/backend/s3_minio/S3_DB__Chat_Threads__Disabled.py
osbot_llms/backend/s3_minio/S3__Chat_Threads.py
osbot_llms/backend/s3_minio/S3__Key__Chat_Thread.py
osbot_llms/backend/s3_minio/__init__.py
osbot_llms/fast_api/Fast_API_Route.py
osbot_llms/fast_api/Fast_API__LLMs.py
osbot_llms/fast_api/__init__.py
osbot_llms/fast_api/routes/Routes__Chat.py
osbot_llms/fast_api/routes/Routes__Info.py
osbot_llms/fast_api/routes/Routes__Json_Prompt.py
osbot_llms/fast_api/routes/Routes__OpenAI.py
osbot_llms/fast_api/routes/__init__.py
osbot_llms/lambdas/__init__.py
osbot_llms/lambdas/handler.py
osbot_llms/llms/API_Open_AI.py
osbot_llms/llms/API_Perplexity.py
osbot_llms/llms/LLMs_API.py
osbot_llms/llms/__init__.py
osbot_llms/llms/actions/LLM__Action__Chat_Completion.py
osbot_llms/llms/actions/__init__.py
osbot_llms/llms/chats/LLM__Chat_Completion__Resolve_Engine.py
osbot_llms/llms/chats/LLM__Platform_Engine.py
osbot_llms/llms/chats/LLM__Platform_Engine__Groq.py
osbot_llms/llms/chats/LLM__Platform_Engine__Mistral.py
osbot_llms/llms/chats/LLM__Platform_Engine__Ollama.py
osbot_llms/llms/chats/LLM__Platform_Engine__Open_Router.py
osbot_llms/llms/chats/LLM__Platform_Engine__SambaNova.py
osbot_llms/llms/chats/LLM__Platform_Engine__Together_AI.py
osbot_llms/llms/chats/__init__.py
osbot_llms/llms/prompt_to_json/Prompt_To_Json__Open_AI.py
osbot_llms/llms/prompt_to_json/__init__.py
osbot_llms/llms/prompt_to_json/use_cases/Json_Prompt__Create_Summary.py
osbot_llms/llms/prompt_to_json/use_cases/Json_Prompt__Document_Improver.py
osbot_llms/llms/prompt_to_json/use_cases/Json_Prompt__Email_Generator.py
osbot_llms/llms/prompt_to_json/use_cases/Json_Prompt__Form_Generator.py
osbot_llms/llms/prompt_to_json/use_cases/Json_Prompt__Graph_Extractor.py
osbot_llms-0.2.21.dist-info/LICENSE
osbot_llms-0.2.21.dist-info/METADATA
osbot_llms-0.2.21.dist-info/WHEEL
osbot_llms-0.2.21.dist-info/RECORD
