Metadata-Version: 2.1
Name: osbot_llms
Version: 0.2.21
Summary: OWASP Security Bot - LLM
Home-page: https://github.com/owasp-sbot/OSBot-LLMs
License: MIT
Author: Dinis Cruz
Author-email: dinis.cruz@owasp.org
Requires-Python: >=3.11,<4.0
Classifier: License :: OSI Approved :: MIT License
Classifier: Programming Language :: Python :: 3
Classifier: Programming Language :: Python :: 3.11
Classifier: Programming Language :: Python :: 3.12
Classifier: Programming Language :: Python :: 3.13
Requires-Dist: httpx
Requires-Dist: mangum
Requires-Dist: numpy
Requires-Dist: openai
Requires-Dist: osbot-aws
Requires-Dist: osbot-fast-api
Requires-Dist: uvicorn
Project-URL: Repository, https://github.com/owasp-sbot/OSBot-LLMs
